README.md
setup.py
cmd_plan/__init__.py
cmd_plan/core.py
cmd_plan.egg-info/PKG-INFO
cmd_plan.egg-info/SOURCES.txt
cmd_plan.egg-info/dependency_links.txt
cmd_plan.egg-info/top_level.txt