Metadata-Version: 2.1
Name: cmd-plan
Version: 1.0.4
Summary: Python3 OS commands run dependency planner
Home-page: UNKNOWN
Author: BorisPlus
Author-email: cmd_plan@borisplus.ru
License: UNKNOWN
Platform: UNKNOWN
Classifier: Programming Language :: Python :: 3
Classifier: Operating System :: OS Independent
Requires-Python: >=3.4
